{
  "count": 40,
  "next": "https://i18n.elypia.org/api/translations/?page=2",
  "previous": null,
  "results": [
    {
      "language": {
        "code": "en",
        "name": "English",
        "plural": {
          "id": 80,
          "source": 0,
          "number": 2,
          "formula": "n != 1",
          "type": 1
        },
        "aliases": [
          "english",
          "en_en",
          "base",
          "source",
          "eng"
        ],
        "direction": "ltr",
        "web_url": "https://i18n.elypia.org/languages/en/",
        "url": "https://i18n.elypia.org/api/languages/en/",
        "statistics_url": "https://i18n.elypia.org/api/languages/en/statistics/"
      },
      "component": {
        "name": "Website",
        "slug": "website",
        "id": 4,
        "project": {
          "name": "Elypia Website",
          "slug": "elypia-website",
          "id": 2,
          "web": "https://elypia.org/",
          "source_language": {
            "code": "en",
            "name": "English",
            "plural": {
              "id": 80,
              "source": 0,
              "number": 2,
              "formula": "n != 1",
              "type": 1
            },
            "aliases": [
              "english",
              "en_en",
              "base",
              "source",
              "eng"
            ],
            "direction": "ltr",
            "web_url": "https://i18n.elypia.org/languages/en/",
            "url": "https://i18n.elypia.org/api/languages/en/",
            "statistics_url": "https://i18n.elypia.org/api/languages/en/statistics/"
          },
          "web_url": "https://i18n.elypia.org/projects/elypia-website/",
          "url": "https://i18n.elypia.org/api/projects/elypia-website/",
          "components_list_url": "https://i18n.elypia.org/api/projects/elypia-website/components/",
          "repository_url": "https://i18n.elypia.org/api/projects/elypia-website/repository/",
          "statistics_url": "https://i18n.elypia.org/api/projects/elypia-website/statistics/",
          "changes_list_url": "https://i18n.elypia.org/api/projects/elypia-website/changes/",
          "languages_url": "https://i18n.elypia.org/api/projects/elypia-website/languages/"
        },
        "vcs": "gitlab",
        "repo": "git@gitlab.com:Elypia/elypia-website.git",
        "git_export": "https://i18n.elypia.org/git/elypia-website/website/",
        "branch": "master",
        "filemask": "src/locales/messages.*.xlf",
        "template": "src/locales/messages.en-US.xlf",
        "edit_template": true,
        "new_base": "src/locales/messages.en-US.xlf",
        "file_format": "xliff",
        "license": "Apache-2.0",
        "license_url": "http://www.apache.org/licenses/LICENSE-2.0",
        "web_url": "https://i18n.elypia.org/projects/elypia-website/website/",
        "url": "https://i18n.elypia.org/api/components/elypia-website/website/",
        "repository_url": "https://i18n.elypia.org/api/components/elypia-website/website/repository/",
        "translations_url": "https://i18n.elypia.org/api/components/elypia-website/website/translations/",
        "statistics_url": "https://i18n.elypia.org/api/components/elypia-website/website/statistics/",
        "lock_url": "https://i18n.elypia.org/api/components/elypia-website/website/lock/",
        "changes_list_url": "https://i18n.elypia.org/api/components/elypia-website/website/changes/",
        "new_lang": "add",
        "push": "",
        "check_flags": "",
        "enforced_checks": "",
        "restricted": false
      },
      "language_code": "en",
      "id": 25,
      "filename": "src/locales/messages.en-US.xlf",
      "revision": "245851b63b17c5a36365d4fe3c90fe2acebae388,245851b63b17c5a36365d4fe3c90fe2acebae388",
      "web_url": "https://i18n.elypia.org/projects/elypia-website/website/en/",
      "share_url": "https://i18n.elypia.org/engage/elypia-website/en/",
      "translate_url": "https://i18n.elypia.org/translate/elypia-website/website/en/",
      "url": "https://i18n.elypia.org/api/translations/elypia-website/website/en/",
      "is_template": true,
      "is_source": true,
      "total": 96,
      "total_words": 1273,
      "translated": 96,
      "translated_words": 1273,
      "translated_percent": 100.0,
      "fuzzy": 0,
      "fuzzy_words": 0,
      "fuzzy_percent": 0.0,
      "failing_checks": 8,
      "failing_checks_words": 40,
      "failing_checks_percent": 8.3,
      "have_suggestion": 0,
      "have_comment": 0,
      "last_change": null,
      "last_author": null,
      "repository_url": "https://i18n.elypia.org/api/translations/elypia-website/website/en/repository/",
      "file_url": "https://i18n.elypia.org/api/translations/elypia-website/website/en/file/",
      "statistics_url": "https://i18n.elypia.org/api/translations/elypia-website/website/en/statistics/",
      "changes_list_url": "https://i18n.elypia.org/api/translations/elypia-website/website/en/changes/",
      "units_list_url": "https://i18n.elypia.org/api/translations/elypia-website/website/en/units/"
    },
    {
      "language": {
        "code": "bs_Latn",
        "name": "Bosnian (latin)",
        "plural": {
          "id": 48,
          "source": 0,
          "number": 3,
          "formula": "n%10==1 && n%100!=11 ? 0 : n%10>=2 && n%10<=4 && (n%100<10 || n%100>=20) ? 1 : 2",
          "type": 2
        },
        "aliases": [
          "bs_latn_ba"
        ],
        "direction": "ltr",
        "web_url": "https://i18n.elypia.org/languages/bs_Latn/",
        "url": "https://i18n.elypia.org/api/languages/bs_Latn/",
        "statistics_url": "https://i18n.elypia.org/api/languages/bs_Latn/statistics/"
      },
      "component": {
        "name": "Website",
        "slug": "website",
        "id": 4,
        "project": {
          "name": "Elypia Website",
          "slug": "elypia-website",
          "id": 2,
          "web": "https://elypia.org/",
          "source_language": {
            "code": "en",
            "name": "English",
            "plural": {
              "id": 80,
              "source": 0,
              "number": 2,
              "formula": "n != 1",
              "type": 1
            },
            "aliases": [
              "english",
              "en_en",
              "base",
              "source",
              "eng"
            ],
            "direction": "ltr",
            "web_url": "https://i18n.elypia.org/languages/en/",
            "url": "https://i18n.elypia.org/api/languages/en/",
            "statistics_url": "https://i18n.elypia.org/api/languages/en/statistics/"
          },
          "web_url": "https://i18n.elypia.org/projects/elypia-website/",
          "url": "https://i18n.elypia.org/api/projects/elypia-website/",
          "components_list_url": "https://i18n.elypia.org/api/projects/elypia-website/components/",
          "repository_url": "https://i18n.elypia.org/api/projects/elypia-website/repository/",
          "statistics_url": "https://i18n.elypia.org/api/projects/elypia-website/statistics/",
          "changes_list_url": "https://i18n.elypia.org/api/projects/elypia-website/changes/",
          "languages_url": "https://i18n.elypia.org/api/projects/elypia-website/languages/"
        },
        "vcs": "gitlab",
        "repo": "git@gitlab.com:Elypia/elypia-website.git",
        "git_export": "https://i18n.elypia.org/git/elypia-website/website/",
        "branch": "master",
        "filemask": "src/locales/messages.*.xlf",
        "template": "src/locales/messages.en-US.xlf",
        "edit_template": true,
        "new_base": "src/locales/messages.en-US.xlf",
        "file_format": "xliff",
        "license": "Apache-2.0",
        "license_url": "http://www.apache.org/licenses/LICENSE-2.0",
        "web_url": "https://i18n.elypia.org/projects/elypia-website/website/",
        "url": "https://i18n.elypia.org/api/components/elypia-website/website/",
        "repository_url": "https://i18n.elypia.org/api/components/elypia-website/website/repository/",
        "translations_url": "https://i18n.elypia.org/api/components/elypia-website/website/translations/",
        "statistics_url": "https://i18n.elypia.org/api/components/elypia-website/website/statistics/",
        "lock_url": "https://i18n.elypia.org/api/components/elypia-website/website/lock/",
        "changes_list_url": "https://i18n.elypia.org/api/components/elypia-website/website/changes/",
        "new_lang": "add",
        "push": "",
        "check_flags": "",
        "enforced_checks": "",
        "restricted": false
      },
      "language_code": "bs-Latn",
      "id": 26,
      "filename": "src/locales/messages.bs-Latn.xlf",
      "revision": "2a90db61852886513350ded334fccc07d9951472,245851b63b17c5a36365d4fe3c90fe2acebae388",
      "web_url": "https://i18n.elypia.org/projects/elypia-website/website/bs_Latn/",
      "share_url": "https://i18n.elypia.org/engage/elypia-website/bs_Latn/",
      "translate_url": "https://i18n.elypia.org/translate/elypia-website/website/bs_Latn/",
      "url": "https://i18n.elypia.org/api/translations/elypia-website/website/bs_Latn/",
      "is_template": false,
      "is_source": false,
      "total": 96,
      "total_words": 1273,
      "translated": 37,
      "translated_words": 262,
      "translated_percent": 38.5,
      "fuzzy": 0,
      "fuzzy_words": 0,
      "fuzzy_percent": 0.0,
      "failing_checks": 2,
      "failing_checks_words": 3,
      "failing_checks_percent": 2.0,
      "have_suggestion": 0,
      "have_comment": 0,
      "last_change": null,
      "last_author": null,
      "repository_url": "https://i18n.elypia.org/api/translations/elypia-website/website/bs_Latn/repository/",
      "file_url": "https://i18n.elypia.org/api/translations/elypia-website/website/bs_Latn/file/",
      "statistics_url": "https://i18n.elypia.org/api/translations/elypia-website/website/bs_Latn/statistics/",
      "changes_list_url": "https://i18n.elypia.org/api/translations/elypia-website/website/bs_Latn/changes/",
      "units_list_url": "https://i18n.elypia.org/api/translations/elypia-website/website/bs_Latn/units/"
    },
    {
      "language": {
        "code": "en_Simple",
        "name": "English",
        "plural": {
          "id": 380,
          "source": 0,
          "number": 2,
          "formula": "n != 1",
          "type": 1
        },
        "aliases": [],
        "direction": "ltr",
        "web_url": "https://i18n.elypia.org/languages/en_Simple/",
        "url": "https://i18n.elypia.org/api/languages/en_Simple/",
        "statistics_url": "https://i18n.elypia.org/api/languages/en_Simple/statistics/"
      },
      "component": {
        "name": "Website",
        "slug": "website",
        "id": 4,
        "project": {
          "name": "Elypia Website",
          "slug": "elypia-website",
          "id": 2,
          "web": "https://elypia.org/",
          "source_language": {
            "code": "en",
            "name": "English",
            "plural": {
              "id": 80,
              "source": 0,
              "number": 2,
              "formula": "n != 1",
              "type": 1
            },
            "aliases": [
              "english",
              "en_en",
              "base",
              "source",
              "eng"
            ],
            "direction": "ltr",
            "web_url": "https://i18n.elypia.org/languages/en/",
            "url": "https://i18n.elypia.org/api/languages/en/",
            "statistics_url": "https://i18n.elypia.org/api/languages/en/statistics/"
          },
          "web_url": "https://i18n.elypia.org/projects/elypia-website/",
          "url": "https://i18n.elypia.org/api/projects/elypia-website/",
          "components_list_url": "https://i18n.elypia.org/api/projects/elypia-website/components/",
          "repository_url": "https://i18n.elypia.org/api/projects/elypia-website/repository/",
          "statistics_url": "https://i18n.elypia.org/api/projects/elypia-website/statistics/",
          "changes_list_url": "https://i18n.elypia.org/api/projects/elypia-website/changes/",
          "languages_url": "https://i18n.elypia.org/api/projects/elypia-website/languages/"
        },
        "vcs": "gitlab",
        "repo": "git@gitlab.com:Elypia/elypia-website.git",
        "git_export": "https://i18n.elypia.org/git/elypia-website/website/",
        "branch": "master",
        "filemask": "src/locales/messages.*.xlf",
        "template": "src/locales/messages.en-US.xlf",
        "edit_template": true,
        "new_base": "src/locales/messages.en-US.xlf",
        "file_format": "xliff",
        "license": "Apache-2.0",
        "license_url": "http://www.apache.org/licenses/LICENSE-2.0",
        "web_url": "https://i18n.elypia.org/projects/elypia-website/website/",
        "url": "https://i18n.elypia.org/api/components/elypia-website/website/",
        "repository_url": "https://i18n.elypia.org/api/components/elypia-website/website/repository/",
        "translations_url": "https://i18n.elypia.org/api/components/elypia-website/website/translations/",
        "statistics_url": "https://i18n.elypia.org/api/components/elypia-website/website/statistics/",
        "lock_url": "https://i18n.elypia.org/api/components/elypia-website/website/lock/",
        "changes_list_url": "https://i18n.elypia.org/api/components/elypia-website/website/changes/",
        "new_lang": "add",
        "push": "",
        "check_flags": "",
        "enforced_checks": "",
        "restricted": false
      },
      "language_code": "en-Simple",
      "id": 27,
      "filename": "src/locales/messages.en-Simple.xlf",
      "revision": "686b034c0ab8b69053aac5a28137f66085607fa1,245851b63b17c5a36365d4fe3c90fe2acebae388",
      "web_url": "https://i18n.elypia.org/projects/elypia-website/website/en_Simple/",
      "share_url": "https://i18n.elypia.org/engage/elypia-website/en_Simple/",
      "translate_url": "https://i18n.elypia.org/translate/elypia-website/website/en_Simple/",
      "url": "https://i18n.elypia.org/api/translations/elypia-website/website/en_Simple/",
      "is_template": false,
      "is_source": false,
      "total": 96,
      "total_words": 1273,
      "translated": 83,
      "translated_words": 803,
      "translated_percent": 86.4,
      "fuzzy": 0,
      "fuzzy_words": 0,
      "fuzzy_percent": 0.0,
      "failing_checks": 7,
      "failing_checks_words": 66,
      "failing_checks_percent": 7.2,
      "have_suggestion": 0,
      "have_comment": 0,
      "last_change": "2020-06-17T04:26:35.626464Z",
      "last_author": "Elypia CIC",
      "repository_url": "https://i18n.elypia.org/api/translations/elypia-website/website/en_Simple/repository/",
      "file_url": "https://i18n.elypia.org/api/translations/elypia-website/website/en_Simple/file/",
      "statistics_url": "https://i18n.elypia.org/api/translations/elypia-website/website/en_Simple/statistics/",
      "changes_list_url": "https://i18n.elypia.org/api/translations/elypia-website/website/en_Simple/changes/",
      "units_list_url": "https://i18n.elypia.org/api/translations/elypia-website/website/en_Simple/units/"
    },
    {
      "language": {
        "code": "fr",
        "name": "French",
        "plural": {
          "id": 113,
          "source": 0,
          "number": 2,
          "formula": "n > 1",
          "type": 1
        },
        "aliases": [
          "french",
          "fra",
          "fre"
        ],
        "direction": "ltr",
        "web_url": "https://i18n.elypia.org/languages/fr/",
        "url": "https://i18n.elypia.org/api/languages/fr/",
        "statistics_url": "https://i18n.elypia.org/api/languages/fr/statistics/"
      },
      "component": {
        "name": "Website",
        "slug": "website",
        "id": 4,
        "project": {
          "name": "Elypia Website",
          "slug": "elypia-website",
          "id": 2,
          "web": "https://elypia.org/",
          "source_language": {
            "code": "en",
            "name": "English",
            "plural": {
              "id": 80,
              "source": 0,
              "number": 2,
              "formula": "n != 1",
              "type": 1
            },
            "aliases": [
              "english",
              "en_en",
              "base",
              "source",
              "eng"
            ],
            "direction": "ltr",
            "web_url": "https://i18n.elypia.org/languages/en/",
            "url": "https://i18n.elypia.org/api/languages/en/",
            "statistics_url": "https://i18n.elypia.org/api/languages/en/statistics/"
          },
          "web_url": "https://i18n.elypia.org/projects/elypia-website/",
          "url": "https://i18n.elypia.org/api/projects/elypia-website/",
          "components_list_url": "https://i18n.elypia.org/api/projects/elypia-website/components/",
          "repository_url": "https://i18n.elypia.org/api/projects/elypia-website/repository/",
          "statistics_url": "https://i18n.elypia.org/api/projects/elypia-website/statistics/",
          "changes_list_url": "https://i18n.elypia.org/api/projects/elypia-website/changes/",
          "languages_url": "https://i18n.elypia.org/api/projects/elypia-website/languages/"
        },
        "vcs": "gitlab",
        "repo": "git@gitlab.com:Elypia/elypia-website.git",
        "git_export": "https://i18n.elypia.org/git/elypia-website/website/",
        "branch": "master",
        "filemask": "src/locales/messages.*.xlf",
        "template": "src/locales/messages.en-US.xlf",
        "edit_template": true,
        "new_base": "src/locales/messages.en-US.xlf",
        "file_format": "xliff",
        "license": "Apache-2.0",
        "license_url": "http://www.apache.org/licenses/LICENSE-2.0",
        "web_url": "https://i18n.elypia.org/projects/elypia-website/website/",
        "url": "https://i18n.elypia.org/api/components/elypia-website/website/",
        "repository_url": "https://i18n.elypia.org/api/components/elypia-website/website/repository/",
        "translations_url": "https://i18n.elypia.org/api/components/elypia-website/website/translations/",
        "statistics_url": "https://i18n.elypia.org/api/components/elypia-website/website/statistics/",
        "lock_url": "https://i18n.elypia.org/api/components/elypia-website/website/lock/",
        "changes_list_url": "https://i18n.elypia.org/api/components/elypia-website/website/changes/",
        "new_lang": "add",
        "push": "",
        "check_flags": "",
        "enforced_checks": "",
        "restricted": false
      },
      "language_code": "fr",
      "id": 28,
      "filename": "src/locales/messages.fr.xlf",
      "revision": "01b0f073fa1d62009bf1bfce063e1bec603fd76a,245851b63b17c5a36365d4fe3c90fe2acebae388",
      "web_url": "https://i18n.elypia.org/projects/elypia-website/website/fr/",
      "share_url": "https://i18n.elypia.org/engage/elypia-website/fr/",
      "translate_url": "https://i18n.elypia.org/translate/elypia-website/website/fr/",
      "url": "https://i18n.elypia.org/api/translations/elypia-website/website/fr/",
      "is_template": false,
      "is_source": false,
      "total": 96,
      "total_words": 1273,
      "translated": 90,
      "translated_words": 1181,
      "translated_percent": 93.7,
      "fuzzy": 0,
      "fuzzy_words": 0,
      "fuzzy_percent": 0.0,
      "failing_checks": 0,
      "failing_checks_words": 0,
      "failing_checks_percent": 0.0,
      "have_suggestion": 0,
      "have_comment": 0,
      "last_change": "2020-06-02T19:30:31.633165Z",
      "last_author": "Margot Freuchet",
      "repository_url": "https://i18n.elypia.org/api/translations/elypia-website/website/fr/repository/",
      "file_url": "https://i18n.elypia.org/api/translations/elypia-website/website/fr/file/",
      "statistics_url": "https://i18n.elypia.org/api/translations/elypia-website/website/fr/statistics/",
      "changes_list_url": "https://i18n.elypia.org/api/translations/elypia-website/website/fr/changes/",
      "units_list_url": "https://i18n.elypia.org/api/translations/elypia-website/website/fr/units/"
    },
    {
      "language": {
        "code": "nl",
        "name": "Dutch",
        "plural": {
          "id": 230,
          "source": 0,
          "number": 2,
          "formula": "n != 1",
          "type": 1
        },
        "aliases": [
          "dut",
          "nld"
        ],
        "direction": "ltr",
        "web_url": "https://i18n.elypia.org/languages/nl/",
        "url": "https://i18n.elypia.org/api/languages/nl/",
        "statistics_url": "https://i18n.elypia.org/api/languages/nl/statistics/"
      },
      "component": {
        "name": "Website",
        "slug": "website",
        "id": 4,
        "project": {
          "name": "Elypia Website",
          "slug": "elypia-website",
          "id": 2,
          "web": "https://elypia.org/",
          "source_language": {
            "code": "en",
            "name": "English",
            "plural": {
              "id": 80,
              "source": 0,
              "number": 2,
              "formula": "n != 1",
              "type": 1
            },
            "aliases": [
              "english",
              "en_en",
              "base",
              "source",
              "eng"
            ],
            "direction": "ltr",
            "web_url": "https://i18n.elypia.org/languages/en/",
            "url": "https://i18n.elypia.org/api/languages/en/",
            "statistics_url": "https://i18n.elypia.org/api/languages/en/statistics/"
          },
          "web_url": "https://i18n.elypia.org/projects/elypia-website/",
          "url": "https://i18n.elypia.org/api/projects/elypia-website/",
          "components_list_url": "https://i18n.elypia.org/api/projects/elypia-website/components/",
          "repository_url": "https://i18n.elypia.org/api/projects/elypia-website/repository/",
          "statistics_url": "https://i18n.elypia.org/api/projects/elypia-website/statistics/",
          "changes_list_url": "https://i18n.elypia.org/api/projects/elypia-website/changes/",
          "languages_url": "https://i18n.elypia.org/api/projects/elypia-website/languages/"
        },
        "vcs": "gitlab",
        "repo": "git@gitlab.com:Elypia/elypia-website.git",
        "git_export": "https://i18n.elypia.org/git/elypia-website/website/",
        "branch": "master",
        "filemask": "src/locales/messages.*.xlf",
        "template": "src/locales/messages.en-US.xlf",
        "edit_template": true,
        "new_base": "src/locales/messages.en-US.xlf",
        "file_format": "xliff",
        "license": "Apache-2.0",
        "license_url": "http://www.apache.org/licenses/LICENSE-2.0",
        "web_url": "https://i18n.elypia.org/projects/elypia-website/website/",
        "url": "https://i18n.elypia.org/api/components/elypia-website/website/",
        "repository_url": "https://i18n.elypia.org/api/components/elypia-website/website/repository/",
        "translations_url": "https://i18n.elypia.org/api/components/elypia-website/website/translations/",
        "statistics_url": "https://i18n.elypia.org/api/components/elypia-website/website/statistics/",
        "lock_url": "https://i18n.elypia.org/api/components/elypia-website/website/lock/",
        "changes_list_url": "https://i18n.elypia.org/api/components/elypia-website/website/changes/",
        "new_lang": "add",
        "push": "",
        "check_flags": "",
        "enforced_checks": "",
        "restricted": false
      },
      "language_code": "nl",
      "id": 29,
      "filename": "src/locales/messages.nl.xlf",
      "revision": "69f809ac7394866d677902f65117e19db7874994,245851b63b17c5a36365d4fe3c90fe2acebae388",
      "web_url": "https://i18n.elypia.org/projects/elypia-website/website/nl/",
      "share_url": "https://i18n.elypia.org/engage/elypia-website/nl/",
      "translate_url": "https://i18n.elypia.org/translate/elypia-website/website/nl/",
      "url": "https://i18n.elypia.org/api/translations/elypia-website/website/nl/",
      "is_template": false,
      "is_source": false,
      "total": 96,
      "total_words": 1273,
      "translated": 79,
      "translated_words": 660,
      "translated_percent": 82.2,
      "fuzzy": 0,
      "fuzzy_words": 0,
      "fuzzy_percent": 0.0,
      "failing_checks": 2,
      "failing_checks_words": 3,
      "failing_checks_percent": 2.0,
      "have_suggestion": 0,
      "have_comment": 0,
      "last_change": null,
      "last_author": null,
      "repository_url": "https://i18n.elypia.org/api/translations/elypia-website/website/nl/repository/",
      "file_url": "https://i18n.elypia.org/api/translations/elypia-website/website/nl/file/",
      "statistics_url": "https://i18n.elypia.org/api/translations/elypia-website/website/nl/statistics/",
      "changes_list_url": "https://i18n.elypia.org/api/translations/elypia-website/website/nl/changes/",
      "units_list_url": "https://i18n.elypia.org/api/translations/elypia-website/website/nl/units/"
    },
    {
      "language": {
        "code": "pl",
        "name": "Polish",
        "plural": {
          "id": 250,
          "source": 0,
          "number": 3,
          "formula": "n==1 ? 0 : n%10>=2 && n%10<=4 && (n%100<10 || n%100>=20) ? 1 : 2",
          "type": 2
        },
        "aliases": [
          "polish",
          "pol"
        ],
        "direction": "ltr",
        "web_url": "https://i18n.elypia.org/languages/pl/",
        "url": "https://i18n.elypia.org/api/languages/pl/",
        "statistics_url": "https://i18n.elypia.org/api/languages/pl/statistics/"
      },
      "component": {
        "name": "Website",
        "slug": "website",
        "id": 4,
        "project": {
          "name": "Elypia Website",
          "slug": "elypia-website",
          "id": 2,
          "web": "https://elypia.org/",
          "source_language": {
            "code": "en",
            "name": "English",
            "plural": {
              "id": 80,
              "source": 0,
              "number": 2,
              "formula": "n != 1",
              "type": 1
            },
            "aliases": [
              "english",
              "en_en",
              "base",
              "source",
              "eng"
            ],
            "direction": "ltr",
            "web_url": "https://i18n.elypia.org/languages/en/",
            "url": "https://i18n.elypia.org/api/languages/en/",
            "statistics_url": "https://i18n.elypia.org/api/languages/en/statistics/"
          },
          "web_url": "https://i18n.elypia.org/projects/elypia-website/",
          "url": "https://i18n.elypia.org/api/projects/elypia-website/",
          "components_list_url": "https://i18n.elypia.org/api/projects/elypia-website/components/",
          "repository_url": "https://i18n.elypia.org/api/projects/elypia-website/repository/",
          "statistics_url": "https://i18n.elypia.org/api/projects/elypia-website/statistics/",
          "changes_list_url": "https://i18n.elypia.org/api/projects/elypia-website/changes/",
          "languages_url": "https://i18n.elypia.org/api/projects/elypia-website/languages/"
        },
        "vcs": "gitlab",
        "repo": "git@gitlab.com:Elypia/elypia-website.git",
        "git_export": "https://i18n.elypia.org/git/elypia-website/website/",
        "branch": "master",
        "filemask": "src/locales/messages.*.xlf",
        "template": "src/locales/messages.en-US.xlf",
        "edit_template": true,
        "new_base": "src/locales/messages.en-US.xlf",
        "file_format": "xliff",
        "license": "Apache-2.0",
        "license_url": "http://www.apache.org/licenses/LICENSE-2.0",
        "web_url": "https://i18n.elypia.org/projects/elypia-website/website/",
        "url": "https://i18n.elypia.org/api/components/elypia-website/website/",
        "repository_url": "https://i18n.elypia.org/api/components/elypia-website/website/repository/",
        "translations_url": "https://i18n.elypia.org/api/components/elypia-website/website/translations/",
        "statistics_url": "https://i18n.elypia.org/api/components/elypia-website/website/statistics/",
        "lock_url": "https://i18n.elypia.org/api/components/elypia-website/website/lock/",
        "changes_list_url": "https://i18n.elypia.org/api/components/elypia-website/website/changes/",
        "new_lang": "add",
        "push": "",
        "check_flags": "",
        "enforced_checks": "",
        "restricted": false
      },
      "language_code": "pl",
      "id": 30,
      "filename": "src/locales/messages.pl.xlf",
      "revision": "102d021a7abc887c7cfa04f4d1c03c5f76974e71,245851b63b17c5a36365d4fe3c90fe2acebae388",
      "web_url": "https://i18n.elypia.org/projects/elypia-website/website/pl/",
      "share_url": "https://i18n.elypia.org/engage/elypia-website/pl/",
      "translate_url": "https://i18n.elypia.org/translate/elypia-website/website/pl/",
      "url": "https://i18n.elypia.org/api/translations/elypia-website/website/pl/",
      "is_template": false,
      "is_source": false,
      "total": 96,
      "total_words": 1273,
      "translated": 90,
      "translated_words": 1181,
      "translated_percent": 93.7,
      "fuzzy": 0,
      "fuzzy_words": 0,
      "fuzzy_percent": 0.0,
      "failing_checks": 0,
      "failing_checks_words": 0,
      "failing_checks_percent": 0.0,
      "have_suggestion": 0,
      "have_comment": 0,
      "last_change": "2020-05-26T17:41:29.812609Z",
      "last_author": "Liental",
      "repository_url": "https://i18n.elypia.org/api/translations/elypia-website/website/pl/repository/",
      "file_url": "https://i18n.elypia.org/api/translations/elypia-website/website/pl/file/",
      "statistics_url": "https://i18n.elypia.org/api/translations/elypia-website/website/pl/statistics/",
      "changes_list_url": "https://i18n.elypia.org/api/translations/elypia-website/website/pl/changes/",
      "units_list_url": "https://i18n.elypia.org/api/translations/elypia-website/website/pl/units/"
    },
    {
      "language": {
        "code": "nb_NO",
        "name": "Norwegian Bokmål",
        "plural": {
          "id": 225,
          "source": 0,
          "number": 2,
          "formula": "n != 1",
          "type": 1
        },
        "aliases": [
          "norwegian",
          "no_nb",
          "no_no",
          "no",
          "nb"
        ],
        "direction": "ltr",
        "web_url": "https://i18n.elypia.org/languages/nb_NO/",
        "url": "https://i18n.elypia.org/api/languages/nb_NO/",
        "statistics_url": "https://i18n.elypia.org/api/languages/nb_NO/statistics/"
      },
      "component": {
        "name": "Website",
        "slug": "website",
        "id": 4,
        "project": {
          "name": "Elypia Website",
          "slug": "elypia-website",
          "id": 2,
          "web": "https://elypia.org/",
          "source_language": {
            "code": "en",
            "name": "English",
            "plural": {
              "id": 80,
              "source": 0,
              "number": 2,
              "formula": "n != 1",
              "type": 1
            },
            "aliases": [
              "english",
              "en_en",
              "base",
              "source",
              "eng"
            ],
            "direction": "ltr",
            "web_url": "https://i18n.elypia.org/languages/en/",
            "url": "https://i18n.elypia.org/api/languages/en/",
            "statistics_url": "https://i18n.elypia.org/api/languages/en/statistics/"
          },
          "web_url": "https://i18n.elypia.org/projects/elypia-website/",
          "url": "https://i18n.elypia.org/api/projects/elypia-website/",
          "components_list_url": "https://i18n.elypia.org/api/projects/elypia-website/components/",
          "repository_url": "https://i18n.elypia.org/api/projects/elypia-website/repository/",
          "statistics_url": "https://i18n.elypia.org/api/projects/elypia-website/statistics/",
          "changes_list_url": "https://i18n.elypia.org/api/projects/elypia-website/changes/",
          "languages_url": "https://i18n.elypia.org/api/projects/elypia-website/languages/"
        },
        "vcs": "gitlab",
        "repo": "git@gitlab.com:Elypia/elypia-website.git",
        "git_export": "https://i18n.elypia.org/git/elypia-website/website/",
        "branch": "master",
        "filemask": "src/locales/messages.*.xlf",
        "template": "src/locales/messages.en-US.xlf",
        "edit_template": true,
        "new_base": "src/locales/messages.en-US.xlf",
        "file_format": "xliff",
        "license": "Apache-2.0",
        "license_url": "http://www.apache.org/licenses/LICENSE-2.0",
        "web_url": "https://i18n.elypia.org/projects/elypia-website/website/",
        "url": "https://i18n.elypia.org/api/components/elypia-website/website/",
        "repository_url": "https://i18n.elypia.org/api/components/elypia-website/website/repository/",
        "translations_url": "https://i18n.elypia.org/api/components/elypia-website/website/translations/",
        "statistics_url": "https://i18n.elypia.org/api/components/elypia-website/website/statistics/",
        "lock_url": "https://i18n.elypia.org/api/components/elypia-website/website/lock/",
        "changes_list_url": "https://i18n.elypia.org/api/components/elypia-website/website/changes/",
        "new_lang": "add",
        "push": "",
        "check_flags": "",
        "enforced_checks": "",
        "restricted": false
      },
      "language_code": "nb-NO",
      "id": 31,
      "filename": "src/locales/messages.nb-NO.xlf",
      "revision": "004e158e7d2f84cd30dcbc05b167314771181ce8,245851b63b17c5a36365d4fe3c90fe2acebae388",
      "web_url": "https://i18n.elypia.org/projects/elypia-website/website/nb_NO/",
      "share_url": "https://i18n.elypia.org/engage/elypia-website/nb_NO/",
      "translate_url": "https://i18n.elypia.org/translate/elypia-website/website/nb_NO/",
      "url": "https://i18n.elypia.org/api/translations/elypia-website/website/nb_NO/",
      "is_template": false,
      "is_source": false,
      "total": 96,
      "total_words": 1273,
      "translated": 25,
      "translated_words": 70,
      "translated_percent": 26.0,
      "fuzzy": 0,
      "fuzzy_words": 0,
      "fuzzy_percent": 0.0,
      "failing_checks": 1,
      "failing_checks_words": 2,
      "failing_checks_percent": 1.0,
      "have_suggestion": 16,
      "have_comment": 0,
      "last_change": "2020-04-28T13:45:17.959682Z",
      "last_author": "Joe Stone",
      "repository_url": "https://i18n.elypia.org/api/translations/elypia-website/website/nb_NO/repository/",
      "file_url": "https://i18n.elypia.org/api/translations/elypia-website/website/nb_NO/file/",
      "statistics_url": "https://i18n.elypia.org/api/translations/elypia-website/website/nb_NO/statistics/",
      "changes_list_url": "https://i18n.elypia.org/api/translations/elypia-website/website/nb_NO/changes/",
      "units_list_url": "https://i18n.elypia.org/api/translations/elypia-website/website/nb_NO/units/"
    },
    {
      "language": {
        "code": "de",
        "name": "German",
        "plural": {
          "id": 70,
          "source": 0,
          "number": 2,
          "formula": "n != 1",
          "type": 1
        },
        "aliases": [
          "german",
          "deu",
          "ger"
        ],
        "direction": "ltr",
        "web_url": "https://i18n.elypia.org/languages/de/",
        "url": "https://i18n.elypia.org/api/languages/de/",
        "statistics_url": "https://i18n.elypia.org/api/languages/de/statistics/"
      },
      "component": {
        "name": "Website",
        "slug": "website",
        "id": 4,
        "project": {
          "name": "Elypia Website",
          "slug": "elypia-website",
          "id": 2,
          "web": "https://elypia.org/",
          "source_language": {
            "code": "en",
            "name": "English",
            "plural": {
              "id": 80,
              "source": 0,
              "number": 2,
              "formula": "n != 1",
              "type": 1
            },
            "aliases": [
              "english",
              "en_en",
              "base",
              "source",
              "eng"
            ],
            "direction": "ltr",
            "web_url": "https://i18n.elypia.org/languages/en/",
            "url": "https://i18n.elypia.org/api/languages/en/",
            "statistics_url": "https://i18n.elypia.org/api/languages/en/statistics/"
          },
          "web_url": "https://i18n.elypia.org/projects/elypia-website/",
          "url": "https://i18n.elypia.org/api/projects/elypia-website/",
          "components_list_url": "https://i18n.elypia.org/api/projects/elypia-website/components/",
          "repository_url": "https://i18n.elypia.org/api/projects/elypia-website/repository/",
          "statistics_url": "https://i18n.elypia.org/api/projects/elypia-website/statistics/",
          "changes_list_url": "https://i18n.elypia.org/api/projects/elypia-website/changes/",
          "languages_url": "https://i18n.elypia.org/api/projects/elypia-website/languages/"
        },
        "vcs": "gitlab",
        "repo": "git@gitlab.com:Elypia/elypia-website.git",
        "git_export": "https://i18n.elypia.org/git/elypia-website/website/",
        "branch": "master",
        "filemask": "src/locales/messages.*.xlf",
        "template": "src/locales/messages.en-US.xlf",
        "edit_template": true,
        "new_base": "src/locales/messages.en-US.xlf",
        "file_format": "xliff",
        "license": "Apache-2.0",
        "license_url": "http://www.apache.org/licenses/LICENSE-2.0",
        "web_url": "https://i18n.elypia.org/projects/elypia-website/website/",
        "url": "https://i18n.elypia.org/api/components/elypia-website/website/",
        "repository_url": "https://i18n.elypia.org/api/components/elypia-website/website/repository/",
        "translations_url": "https://i18n.elypia.org/api/components/elypia-website/website/translations/",
        "statistics_url": "https://i18n.elypia.org/api/components/elypia-website/website/statistics/",
        "lock_url": "https://i18n.elypia.org/api/components/elypia-website/website/lock/",
        "changes_list_url": "https://i18n.elypia.org/api/components/elypia-website/website/changes/",
        "new_lang": "add",
        "push": "",
        "check_flags": "",
        "enforced_checks": "",
        "restricted": false
      },
      "language_code": "de",
      "id": 32,
      "filename": "src/locales/messages.de.xlf",
      "revision": "c8a2992aa3300bb8acb40e7c8175af613773f20b,245851b63b17c5a36365d4fe3c90fe2acebae388",
      "web_url": "https://i18n.elypia.org/projects/elypia-website/website/de/",
      "share_url": "https://i18n.elypia.org/engage/elypia-website/de/",
      "translate_url": "https://i18n.elypia.org/translate/elypia-website/website/de/",
      "url": "https://i18n.elypia.org/api/translations/elypia-website/website/de/",
      "is_template": false,
      "is_source": false,
      "total": 96,
      "total_words": 1273,
      "translated": 0,
      "translated_words": 0,
      "translated_percent": 0.0,
      "fuzzy": 0,
      "fuzzy_words": 0,
      "fuzzy_percent": 0.0,
      "failing_checks": 0,
      "failing_checks_words": 0,
      "failing_checks_percent": 0.0,
      "have_suggestion": 0,
      "have_comment": 0,
      "last_change": null,
      "last_author": null,
      "repository_url": "https://i18n.elypia.org/api/translations/elypia-website/website/de/repository/",
      "file_url": "https://i18n.elypia.org/api/translations/elypia-website/website/de/file/",
      "statistics_url": "https://i18n.elypia.org/api/translations/elypia-website/website/de/statistics/",
      "changes_list_url": "https://i18n.elypia.org/api/translations/elypia-website/website/de/changes/",
      "units_list_url": "https://i18n.elypia.org/api/translations/elypia-website/website/de/units/"
    },
    {
      "language": {
        "code": "en",
        "name": "English",
        "plural": {
          "id": 80,
          "source": 0,
          "number": 2,
          "formula": "n != 1",
          "type": 1
        },
        "aliases": [
          "english",
          "en_en",
          "base",
          "source",
          "eng"
        ],
        "direction": "ltr",
        "web_url": "https://i18n.elypia.org/languages/en/",
        "url": "https://i18n.elypia.org/api/languages/en/",
        "statistics_url": "https://i18n.elypia.org/api/languages/en/statistics/"
      },
      "component": {
        "name": "Alexis Messages",
        "slug": "alexis-messages",
        "id": 6,
        "project": {
          "name": "Alexis",
          "slug": "alexis",
          "id": 5,
          "web": "https://elypia.org/",
          "source_language": {
            "code": "en",
            "name": "English",
            "plural": {
              "id": 80,
              "source": 0,
              "number": 2,
              "formula": "n != 1",
              "type": 1
            },
            "aliases": [
              "english",
              "en_en",
              "base",
              "source",
              "eng"
            ],
            "direction": "ltr",
            "web_url": "https://i18n.elypia.org/languages/en/",
            "url": "https://i18n.elypia.org/api/languages/en/",
            "statistics_url": "https://i18n.elypia.org/api/languages/en/statistics/"
          },
          "web_url": "https://i18n.elypia.org/projects/alexis/",
          "url": "https://i18n.elypia.org/api/projects/alexis/",
          "components_list_url": "https://i18n.elypia.org/api/projects/alexis/components/",
          "repository_url": "https://i18n.elypia.org/api/projects/alexis/repository/",
          "statistics_url": "https://i18n.elypia.org/api/projects/alexis/statistics/",
          "changes_list_url": "https://i18n.elypia.org/api/projects/alexis/changes/",
          "languages_url": "https://i18n.elypia.org/api/projects/alexis/languages/"
        },
        "vcs": "gitlab",
        "repo": "git@gitlab.com:Elypia/alexis.git",
        "git_export": "https://i18n.elypia.org/git/alexis/alexis-messages/",
        "branch": "master",
        "filemask": "core/src/main/resources/org/elypia/alexis/i18n/AlexisMessages_*.properties",
        "template": "core/src/main/resources/org/elypia/alexis/i18n/AlexisMessages.properties",
        "edit_template": true,
        "new_base": "",
        "file_format": "properties-utf8",
        "license": "Apache-2.0",
        "license_url": "http://www.apache.org/licenses/LICENSE-2.0",
        "web_url": "https://i18n.elypia.org/projects/alexis/alexis-messages/",
        "url": "https://i18n.elypia.org/api/components/alexis/alexis-messages/",
        "repository_url": "https://i18n.elypia.org/api/components/alexis/alexis-messages/repository/",
        "translations_url": "https://i18n.elypia.org/api/components/alexis/alexis-messages/translations/",
        "statistics_url": "https://i18n.elypia.org/api/components/alexis/alexis-messages/statistics/",
        "lock_url": "https://i18n.elypia.org/api/components/alexis/alexis-messages/lock/",
        "changes_list_url": "https://i18n.elypia.org/api/components/alexis/alexis-messages/changes/",
        "new_lang": "add",
        "push": "",
        "check_flags": "",
        "enforced_checks": "",
        "restricted": false
      },
      "language_code": "en",
      "id": 62,
      "filename": "core/src/main/resources/org/elypia/alexis/i18n/AlexisMessages.properties",
      "revision": "a7a32c6b95988dca3a87e8c713a7f04613689228,a7a32c6b95988dca3a87e8c713a7f04613689228",
      "web_url": "https://i18n.elypia.org/projects/alexis/alexis-messages/en/",
      "share_url": "https://i18n.elypia.org/engage/alexis/en/",
      "translate_url": "https://i18n.elypia.org/translate/alexis/alexis-messages/en/",
      "url": "https://i18n.elypia.org/api/translations/alexis/alexis-messages/en/",
      "is_template": true,
      "is_source": true,
      "total": 202,
      "total_words": 1360,
      "translated": 202,
      "translated_words": 1360,
      "translated_percent": 100.0,
      "fuzzy": 0,
      "fuzzy_words": 0,
      "fuzzy_percent": 0.0,
      "failing_checks": 16,
      "failing_checks_words": 136,
      "failing_checks_percent": 7.9,
      "have_suggestion": 0,
      "have_comment": 0,
      "last_change": null,
      "last_author": null,
      "repository_url": "https://i18n.elypia.org/api/translations/alexis/alexis-messages/en/repository/",
      "file_url": "https://i18n.elypia.org/api/translations/alexis/alexis-messages/en/file/",
      "statistics_url": "https://i18n.elypia.org/api/translations/alexis/alexis-messages/en/statistics/",
      "changes_list_url": "https://i18n.elypia.org/api/translations/alexis/alexis-messages/en/changes/",
      "units_list_url": "https://i18n.elypia.org/api/translations/alexis/alexis-messages/en/units/"
    },
    {
      "language": {
        "code": "bs",
        "name": "Bosnian",
        "plural": {
          "id": 46,
          "source": 0,
          "number": 3,
          "formula": "n%10==1 && n%100!=11 ? 0 : n%10>=2 && n%10<=4 && (n%100<10 || n%100>=20) ? 1 : 2",
          "type": 2
        },
        "aliases": [
          "bos"
        ],
        "direction": "ltr",
        "web_url": "https://i18n.elypia.org/languages/bs/",
        "url": "https://i18n.elypia.org/api/languages/bs/",
        "statistics_url": "https://i18n.elypia.org/api/languages/bs/statistics/"
      },
      "component": {
        "name": "Alexis Messages",
        "slug": "alexis-messages",
        "id": 6,
        "project": {
          "name": "Alexis",
          "slug": "alexis",
          "id": 5,
          "web": "https://elypia.org/",
          "source_language": {
            "code": "en",
            "name": "English",
            "plural": {
              "id": 80,
              "source": 0,
              "number": 2,
              "formula": "n != 1",
              "type": 1
            },
            "aliases": [
              "english",
              "en_en",
              "base",
              "source",
              "eng"
            ],
            "direction": "ltr",
            "web_url": "https://i18n.elypia.org/languages/en/",
            "url": "https://i18n.elypia.org/api/languages/en/",
            "statistics_url": "https://i18n.elypia.org/api/languages/en/statistics/"
          },
          "web_url": "https://i18n.elypia.org/projects/alexis/",
          "url": "https://i18n.elypia.org/api/projects/alexis/",
          "components_list_url": "https://i18n.elypia.org/api/projects/alexis/components/",
          "repository_url": "https://i18n.elypia.org/api/projects/alexis/repository/",
          "statistics_url": "https://i18n.elypia.org/api/projects/alexis/statistics/",
          "changes_list_url": "https://i18n.elypia.org/api/projects/alexis/changes/",
          "languages_url": "https://i18n.elypia.org/api/projects/alexis/languages/"
        },
        "vcs": "gitlab",
        "repo": "git@gitlab.com:Elypia/alexis.git",
        "git_export": "https://i18n.elypia.org/git/alexis/alexis-messages/",
        "branch": "master",
        "filemask": "core/src/main/resources/org/elypia/alexis/i18n/AlexisMessages_*.properties",
        "template": "core/src/main/resources/org/elypia/alexis/i18n/AlexisMessages.properties",
        "edit_template": true,
        "new_base": "",
        "file_format": "properties-utf8",
        "license": "Apache-2.0",
        "license_url": "http://www.apache.org/licenses/LICENSE-2.0",
        "web_url": "https://i18n.elypia.org/projects/alexis/alexis-messages/",
        "url": "https://i18n.elypia.org/api/components/alexis/alexis-messages/",
        "repository_url": "https://i18n.elypia.org/api/components/alexis/alexis-messages/repository/",
        "translations_url": "https://i18n.elypia.org/api/components/alexis/alexis-messages/translations/",
        "statistics_url": "https://i18n.elypia.org/api/components/alexis/alexis-messages/statistics/",
        "lock_url": "https://i18n.elypia.org/api/components/alexis/alexis-messages/lock/",
        "changes_list_url": "https://i18n.elypia.org/api/components/alexis/alexis-messages/changes/",
        "new_lang": "add",
        "push": "",
        "check_flags": "",
        "enforced_checks": "",
        "restricted": false
      },
      "language_code": "bs",
      "id": 63,
      "filename": "core/src/main/resources/org/elypia/alexis/i18n/AlexisMessages_bs.properties",
      "revision": "3ad0d02012fce63180170aac07393d212601c4af,a7a32c6b95988dca3a87e8c713a7f04613689228",
      "web_url": "https://i18n.elypia.org/projects/alexis/alexis-messages/bs/",
      "share_url": "https://i18n.elypia.org/engage/alexis/bs/",
      "translate_url": "https://i18n.elypia.org/translate/alexis/alexis-messages/bs/",
      "url": "https://i18n.elypia.org/api/translations/alexis/alexis-messages/bs/",
      "is_template": false,
      "is_source": false,
      "total": 202,
      "total_words": 1360,
      "translated": 64,
      "translated_words": 447,
      "translated_percent": 31.6,
      "fuzzy": 0,
      "fuzzy_words": 0,
      "fuzzy_percent": 0.0,
      "failing_checks": 6,
      "failing_checks_words": 36,
      "failing_checks_percent": 2.9,
      "have_suggestion": 0,
      "have_comment": 0,
      "last_change": null,
      "last_author": null,
      "repository_url": "https://i18n.elypia.org/api/translations/alexis/alexis-messages/bs/repository/",
      "file_url": "https://i18n.elypia.org/api/translations/alexis/alexis-messages/bs/file/",
      "statistics_url": "https://i18n.elypia.org/api/translations/alexis/alexis-messages/bs/statistics/",
      "changes_list_url": "https://i18n.elypia.org/api/translations/alexis/alexis-messages/bs/changes/",
      "units_list_url": "https://i18n.elypia.org/api/translations/alexis/alexis-messages/bs/units/"
    },
    {
      "language": {
        "code": "da",
        "name": "Danish",
        "plural": {
          "id": 69,
          "source": 0,
          "number": 2,
          "formula": "n != 1",
          "type": 1
        },
        "aliases": [
          "dk",
          "dan"
        ],
        "direction": "ltr",
        "web_url": "https://i18n.elypia.org/languages/da/",
        "url": "https://i18n.elypia.org/api/languages/da/",
        "statistics_url": "https://i18n.elypia.org/api/languages/da/statistics/"
      },
      "component": {
        "name": "Alexis Messages",
        "slug": "alexis-messages",
        "id": 6,
        "project": {
          "name": "Alexis",
          "slug": "alexis",
          "id": 5,
          "web": "https://elypia.org/",
          "source_language": {
            "code": "en",
            "name": "English",
            "plural": {
              "id": 80,
              "source": 0,
              "number": 2,
              "formula": "n != 1",
              "type": 1
            },
            "aliases": [
              "english",
              "en_en",
              "base",
              "source",
              "eng"
            ],
            "direction": "ltr",
            "web_url": "https://i18n.elypia.org/languages/en/",
            "url": "https://i18n.elypia.org/api/languages/en/",
            "statistics_url": "https://i18n.elypia.org/api/languages/en/statistics/"
          },
          "web_url": "https://i18n.elypia.org/projects/alexis/",
          "url": "https://i18n.elypia.org/api/projects/alexis/",
          "components_list_url": "https://i18n.elypia.org/api/projects/alexis/components/",
          "repository_url": "https://i18n.elypia.org/api/projects/alexis/repository/",
          "statistics_url": "https://i18n.elypia.org/api/projects/alexis/statistics/",
          "changes_list_url": "https://i18n.elypia.org/api/projects/alexis/changes/",
          "languages_url": "https://i18n.elypia.org/api/projects/alexis/languages/"
        },
        "vcs": "gitlab",
        "repo": "git@gitlab.com:Elypia/alexis.git",
        "git_export": "https://i18n.elypia.org/git/alexis/alexis-messages/",
        "branch": "master",
        "filemask": "core/src/main/resources/org/elypia/alexis/i18n/AlexisMessages_*.properties",
        "template": "core/src/main/resources/org/elypia/alexis/i18n/AlexisMessages.properties",
        "edit_template": true,
        "new_base": "",
        "file_format": "properties-utf8",
        "license": "Apache-2.0",
        "license_url": "http://www.apache.org/licenses/LICENSE-2.0",
        "web_url": "https://i18n.elypia.org/projects/alexis/alexis-messages/",
        "url": "https://i18n.elypia.org/api/components/alexis/alexis-messages/",
        "repository_url": "https://i18n.elypia.org/api/components/alexis/alexis-messages/repository/",
        "translations_url": "https://i18n.elypia.org/api/components/alexis/alexis-messages/translations/",
        "statistics_url": "https://i18n.elypia.org/api/components/alexis/alexis-messages/statistics/",
        "lock_url": "https://i18n.elypia.org/api/components/alexis/alexis-messages/lock/",
        "changes_list_url": "https://i18n.elypia.org/api/components/alexis/alexis-messages/changes/",
        "new_lang": "add",
        "push": "",
        "check_flags": "",
        "enforced_checks": "",
        "restricted": false
      },
      "language_code": "da",
      "id": 64,
      "filename": "core/src/main/resources/org/elypia/alexis/i18n/AlexisMessages_da.properties",
      "revision": "ded49dcf43b84e1f8415696b5eef25b230a62cf0,a7a32c6b95988dca3a87e8c713a7f04613689228",
      "web_url": "https://i18n.elypia.org/projects/alexis/alexis-messages/da/",
      "share_url": "https://i18n.elypia.org/engage/alexis/da/",
      "translate_url": "https://i18n.elypia.org/translate/alexis/alexis-messages/da/",
      "url": "https://i18n.elypia.org/api/translations/alexis/alexis-messages/da/",
      "is_template": false,
      "is_source": false,
      "total": 202,
      "total_words": 1360,
      "translated": 1,
      "translated_words": 10,
      "translated_percent": 0.4,
      "fuzzy": 0,
      "fuzzy_words": 0,
      "fuzzy_percent": 0.0,
      "failing_checks": 1,
      "failing_checks_words": 10,
      "failing_checks_percent": 0.4,
      "have_suggestion": 0,
      "have_comment": 0,
      "last_change": null,
      "last_author": null,
      "repository_url": "https://i18n.elypia.org/api/translations/alexis/alexis-messages/da/repository/",
      "file_url": "https://i18n.elypia.org/api/translations/alexis/alexis-messages/da/file/",
      "statistics_url": "https://i18n.elypia.org/api/translations/alexis/alexis-messages/da/statistics/",
      "changes_list_url": "https://i18n.elypia.org/api/translations/alexis/alexis-messages/da/changes/",
      "units_list_url": "https://i18n.elypia.org/api/translations/alexis/alexis-messages/da/units/"
    },
    {
      "language": {
        "code": "de",
        "name": "German",
        "plural": {
          "id": 70,
          "source": 0,
          "number": 2,
          "formula": "n != 1",
          "type": 1
        },
        "aliases": [
          "german",
          "deu",
          "ger"
        ],
        "direction": "ltr",
        "web_url": "https://i18n.elypia.org/languages/de/",
        "url": "https://i18n.elypia.org/api/languages/de/",
        "statistics_url": "https://i18n.elypia.org/api/languages/de/statistics/"
      },
      "component": {
        "name": "Alexis Messages",
        "slug": "alexis-messages",
        "id": 6,
        "project": {
          "name": "Alexis",
          "slug": "alexis",
          "id": 5,
          "web": "https://elypia.org/",
          "source_language": {
            "code": "en",
            "name": "English",
            "plural": {
              "id": 80,
              "source": 0,
              "number": 2,
              "formula": "n != 1",
              "type": 1
            },
            "aliases": [
              "english",
              "en_en",
              "base",
              "source",
              "eng"
            ],
            "direction": "ltr",
            "web_url": "https://i18n.elypia.org/languages/en/",
            "url": "https://i18n.elypia.org/api/languages/en/",
            "statistics_url": "https://i18n.elypia.org/api/languages/en/statistics/"
          },
          "web_url": "https://i18n.elypia.org/projects/alexis/",
          "url": "https://i18n.elypia.org/api/projects/alexis/",
          "components_list_url": "https://i18n.elypia.org/api/projects/alexis/components/",
          "repository_url": "https://i18n.elypia.org/api/projects/alexis/repository/",
          "statistics_url": "https://i18n.elypia.org/api/projects/alexis/statistics/",
          "changes_list_url": "https://i18n.elypia.org/api/projects/alexis/changes/",
          "languages_url": "https://i18n.elypia.org/api/projects/alexis/languages/"
        },
        "vcs": "gitlab",
        "repo": "git@gitlab.com:Elypia/alexis.git",
        "git_export": "https://i18n.elypia.org/git/alexis/alexis-messages/",
        "branch": "master",
        "filemask": "core/src/main/resources/org/elypia/alexis/i18n/AlexisMessages_*.properties",
        "template": "core/src/main/resources/org/elypia/alexis/i18n/AlexisMessages.properties",
        "edit_template": true,
        "new_base": "",
        "file_format": "properties-utf8",
        "license": "Apache-2.0",
        "license_url": "http://www.apache.org/licenses/LICENSE-2.0",
        "web_url": "https://i18n.elypia.org/projects/alexis/alexis-messages/",
        "url": "https://i18n.elypia.org/api/components/alexis/alexis-messages/",
        "repository_url": "https://i18n.elypia.org/api/components/alexis/alexis-messages/repository/",
        "translations_url": "https://i18n.elypia.org/api/components/alexis/alexis-messages/translations/",
        "statistics_url": "https://i18n.elypia.org/api/components/alexis/alexis-messages/statistics/",
        "lock_url": "https://i18n.elypia.org/api/components/alexis/alexis-messages/lock/",
        "changes_list_url": "https://i18n.elypia.org/api/components/alexis/alexis-messages/changes/",
        "new_lang": "add",
        "push": "",
        "check_flags": "",
        "enforced_checks": "",
        "restricted": false
      },
      "language_code": "de",
      "id": 65,
      "filename": "core/src/main/resources/org/elypia/alexis/i18n/AlexisMessages_de.properties",
      "revision": "00a9fbbd0c75c2d26a499a9c8a9cde3f9839c4a3,a7a32c6b95988dca3a87e8c713a7f04613689228",
      "web_url": "https://i18n.elypia.org/projects/alexis/alexis-messages/de/",
      "share_url": "https://i18n.elypia.org/engage/alexis/de/",
      "translate_url": "https://i18n.elypia.org/translate/alexis/alexis-messages/de/",
      "url": "https://i18n.elypia.org/api/translations/alexis/alexis-messages/de/",
      "is_template": false,
      "is_source": false,
      "total": 202,
      "total_words": 1360,
      "translated": 84,
      "translated_words": 562,
      "translated_percent": 41.5,
      "fuzzy": 0,
      "fuzzy_words": 0,
      "fuzzy_percent": 0.0,
      "failing_checks": 13,
      "failing_checks_words": 96,
      "failing_checks_percent": 6.4,
      "have_suggestion": 0,
      "have_comment": 0,
      "last_change": null,
      "last_author": null,
      "repository_url": "https://i18n.elypia.org/api/translations/alexis/alexis-messages/de/repository/",
      "file_url": "https://i18n.elypia.org/api/translations/alexis/alexis-messages/de/file/",
      "statistics_url": "https://i18n.elypia.org/api/translations/alexis/alexis-messages/de/statistics/",
      "changes_list_url": "https://i18n.elypia.org/api/translations/alexis/alexis-messages/de/changes/",
      "units_list_url": "https://i18n.elypia.org/api/translations/alexis/alexis-messages/de/units/"
    },
    {
      "language": {
        "code": "fr",
        "name": "French",
        "plural": {
          "id": 113,
          "source": 0,
          "number": 2,
          "formula": "n > 1",
          "type": 1
        },
        "aliases": [
          "french",
          "fra",
          "fre"
        ],
        "direction": "ltr",
        "web_url": "https://i18n.elypia.org/languages/fr/",
        "url": "https://i18n.elypia.org/api/languages/fr/",
        "statistics_url": "https://i18n.elypia.org/api/languages/fr/statistics/"
      },
      "component": {
        "name": "Alexis Messages",
        "slug": "alexis-messages",
        "id": 6,
        "project": {
          "name": "Alexis",
          "slug": "alexis",
          "id": 5,
          "web": "https://elypia.org/",
          "source_language": {
            "code": "en",
            "name": "English",
            "plural": {
              "id": 80,
              "source": 0,
              "number": 2,
              "formula": "n != 1",
              "type": 1
            },
            "aliases": [
              "english",
              "en_en",
              "base",
              "source",
              "eng"
            ],
            "direction": "ltr",
            "web_url": "https://i18n.elypia.org/languages/en/",
            "url": "https://i18n.elypia.org/api/languages/en/",
            "statistics_url": "https://i18n.elypia.org/api/languages/en/statistics/"
          },
          "web_url": "https://i18n.elypia.org/projects/alexis/",
          "url": "https://i18n.elypia.org/api/projects/alexis/",
          "components_list_url": "https://i18n.elypia.org/api/projects/alexis/components/",
          "repository_url": "https://i18n.elypia.org/api/projects/alexis/repository/",
          "statistics_url": "https://i18n.elypia.org/api/projects/alexis/statistics/",
          "changes_list_url": "https://i18n.elypia.org/api/projects/alexis/changes/",
          "languages_url": "https://i18n.elypia.org/api/projects/alexis/languages/"
        },
        "vcs": "gitlab",
        "repo": "git@gitlab.com:Elypia/alexis.git",
        "git_export": "https://i18n.elypia.org/git/alexis/alexis-messages/",
        "branch": "master",
        "filemask": "core/src/main/resources/org/elypia/alexis/i18n/AlexisMessages_*.properties",
        "template": "core/src/main/resources/org/elypia/alexis/i18n/AlexisMessages.properties",
        "edit_template": true,
        "new_base": "",
        "file_format": "properties-utf8",
        "license": "Apache-2.0",
        "license_url": "http://www.apache.org/licenses/LICENSE-2.0",
        "web_url": "https://i18n.elypia.org/projects/alexis/alexis-messages/",
        "url": "https://i18n.elypia.org/api/components/alexis/alexis-messages/",
        "repository_url": "https://i18n.elypia.org/api/components/alexis/alexis-messages/repository/",
        "translations_url": "https://i18n.elypia.org/api/components/alexis/alexis-messages/translations/",
        "statistics_url": "https://i18n.elypia.org/api/components/alexis/alexis-messages/statistics/",
        "lock_url": "https://i18n.elypia.org/api/components/alexis/alexis-messages/lock/",
        "changes_list_url": "https://i18n.elypia.org/api/components/alexis/alexis-messages/changes/",
        "new_lang": "add",
        "push": "",
        "check_flags": "",
        "enforced_checks": "",
        "restricted": false
      },
      "language_code": "fr",
      "id": 66,
      "filename": "core/src/main/resources/org/elypia/alexis/i18n/AlexisMessages_fr.properties",
      "revision": "1f2ce78b45a39cbf4f4e2ef5430835d286639677,a7a32c6b95988dca3a87e8c713a7f04613689228",
      "web_url": "https://i18n.elypia.org/projects/alexis/alexis-messages/fr/",
      "share_url": "https://i18n.elypia.org/engage/alexis/fr/",
      "translate_url": "https://i18n.elypia.org/translate/alexis/alexis-messages/fr/",
      "url": "https://i18n.elypia.org/api/translations/alexis/alexis-messages/fr/",
      "is_template": false,
      "is_source": false,
      "total": 202,
      "total_words": 1360,
      "translated": 199,
      "translated_words": 1332,
      "translated_percent": 98.5,
      "fuzzy": 0,
      "fuzzy_words": 0,
      "fuzzy_percent": 0.0,
      "failing_checks": 6,
      "failing_checks_words": 17,
      "failing_checks_percent": 2.9,
      "have_suggestion": 0,
      "have_comment": 0,
      "last_change": null,
      "last_author": null,
      "repository_url": "https://i18n.elypia.org/api/translations/alexis/alexis-messages/fr/repository/",
      "file_url": "https://i18n.elypia.org/api/translations/alexis/alexis-messages/fr/file/",
      "statistics_url": "https://i18n.elypia.org/api/translations/alexis/alexis-messages/fr/statistics/",
      "changes_list_url": "https://i18n.elypia.org/api/translations/alexis/alexis-messages/fr/changes/",
      "units_list_url": "https://i18n.elypia.org/api/translations/alexis/alexis-messages/fr/units/"
    },
    {
      "language": {
        "code": "nl",
        "name": "Dutch",
        "plural": {
          "id": 230,
          "source": 0,
          "number": 2,
          "formula": "n != 1",
          "type": 1
        },
        "aliases": [
          "dut",
          "nld"
        ],
        "direction": "ltr",
        "web_url": "https://i18n.elypia.org/languages/nl/",
        "url": "https://i18n.elypia.org/api/languages/nl/",
        "statistics_url": "https://i18n.elypia.org/api/languages/nl/statistics/"
      },
      "component": {
        "name": "Alexis Messages",
        "slug": "alexis-messages",
        "id": 6,
        "project": {
          "name": "Alexis",
          "slug": "alexis",
          "id": 5,
          "web": "https://elypia.org/",
          "source_language": {
            "code": "en",
            "name": "English",
            "plural": {
              "id": 80,
              "source": 0,
              "number": 2,
              "formula": "n != 1",
              "type": 1
            },
            "aliases": [
              "english",
              "en_en",
              "base",
              "source",
              "eng"
            ],
            "direction": "ltr",
            "web_url": "https://i18n.elypia.org/languages/en/",
            "url": "https://i18n.elypia.org/api/languages/en/",
            "statistics_url": "https://i18n.elypia.org/api/languages/en/statistics/"
          },
          "web_url": "https://i18n.elypia.org/projects/alexis/",
          "url": "https://i18n.elypia.org/api/projects/alexis/",
          "components_list_url": "https://i18n.elypia.org/api/projects/alexis/components/",
          "repository_url": "https://i18n.elypia.org/api/projects/alexis/repository/",
          "statistics_url": "https://i18n.elypia.org/api/projects/alexis/statistics/",
          "changes_list_url": "https://i18n.elypia.org/api/projects/alexis/changes/",
          "languages_url": "https://i18n.elypia.org/api/projects/alexis/languages/"
        },
        "vcs": "gitlab",
        "repo": "git@gitlab.com:Elypia/alexis.git",
        "git_export": "https://i18n.elypia.org/git/alexis/alexis-messages/",
        "branch": "master",
        "filemask": "core/src/main/resources/org/elypia/alexis/i18n/AlexisMessages_*.properties",
        "template": "core/src/main/resources/org/elypia/alexis/i18n/AlexisMessages.properties",
        "edit_template": true,
        "new_base": "",
        "file_format": "properties-utf8",
        "license": "Apache-2.0",
        "license_url": "http://www.apache.org/licenses/LICENSE-2.0",
        "web_url": "https://i18n.elypia.org/projects/alexis/alexis-messages/",
        "url": "https://i18n.elypia.org/api/components/alexis/alexis-messages/",
        "repository_url": "https://i18n.elypia.org/api/components/alexis/alexis-messages/repository/",
        "translations_url": "https://i18n.elypia.org/api/components/alexis/alexis-messages/translations/",
        "statistics_url": "https://i18n.elypia.org/api/components/alexis/alexis-messages/statistics/",
        "lock_url": "https://i18n.elypia.org/api/components/alexis/alexis-messages/lock/",
        "changes_list_url": "https://i18n.elypia.org/api/components/alexis/alexis-messages/changes/",
        "new_lang": "add",
        "push": "",
        "check_flags": "",
        "enforced_checks": "",
        "restricted": false
      },
      "language_code": "nl",
      "id": 67,
      "filename": "core/src/main/resources/org/elypia/alexis/i18n/AlexisMessages_nl.properties",
      "revision": "1282c899d6fe85285579d7185a2ee5f055a54156,a7a32c6b95988dca3a87e8c713a7f04613689228",
      "web_url": "https://i18n.elypia.org/projects/alexis/alexis-messages/nl/",
      "share_url": "https://i18n.elypia.org/engage/alexis/nl/",
      "translate_url": "https://i18n.elypia.org/translate/alexis/alexis-messages/nl/",
      "url": "https://i18n.elypia.org/api/translations/alexis/alexis-messages/nl/",
      "is_template": false,
      "is_source": false,
      "total": 202,
      "total_words": 1360,
      "translated": 84,
      "translated_words": 557,
      "translated_percent": 41.5,
      "fuzzy": 0,
      "fuzzy_words": 0,
      "fuzzy_percent": 0.0,
      "failing_checks": 9,
      "failing_checks_words": 62,
      "failing_checks_percent": 4.4,
      "have_suggestion": 0,
      "have_comment": 0,
      "last_change": null,
      "last_author": null,
      "repository_url": "https://i18n.elypia.org/api/translations/alexis/alexis-messages/nl/repository/",
      "file_url": "https://i18n.elypia.org/api/translations/alexis/alexis-messages/nl/file/",
      "statistics_url": "https://i18n.elypia.org/api/translations/alexis/alexis-messages/nl/statistics/",
      "changes_list_url": "https://i18n.elypia.org/api/translations/alexis/alexis-messages/nl/changes/",
      "units_list_url": "https://i18n.elypia.org/api/translations/alexis/alexis-messages/nl/units/"
    },
    {
      "language": {
        "code": "nb_NO",
        "name": "Norwegian Bokmål",
        "plural": {
          "id": 225,
          "source": 0,
          "number": 2,
          "formula": "n != 1",
          "type": 1
        },
        "aliases": [
          "norwegian",
          "no_nb",
          "no_no",
          "no",
          "nb"
        ],
        "direction": "ltr",
        "web_url": "https://i18n.elypia.org/languages/nb_NO/",
        "url": "https://i18n.elypia.org/api/languages/nb_NO/",
        "statistics_url": "https://i18n.elypia.org/api/languages/nb_NO/statistics/"
      },
      "component": {
        "name": "Alexis Messages",
        "slug": "alexis-messages",
        "id": 6,
        "project": {
          "name": "Alexis",
          "slug": "alexis",
          "id": 5,
          "web": "https://elypia.org/",
          "source_language": {
            "code": "en",
            "name": "English",
            "plural": {
              "id": 80,
              "source": 0,
              "number": 2,
              "formula": "n != 1",
              "type": 1
            },
            "aliases": [
              "english",
              "en_en",
              "base",
              "source",
              "eng"
            ],
            "direction": "ltr",
            "web_url": "https://i18n.elypia.org/languages/en/",
            "url": "https://i18n.elypia.org/api/languages/en/",
            "statistics_url": "https://i18n.elypia.org/api/languages/en/statistics/"
          },
          "web_url": "https://i18n.elypia.org/projects/alexis/",
          "url": "https://i18n.elypia.org/api/projects/alexis/",
          "components_list_url": "https://i18n.elypia.org/api/projects/alexis/components/",
          "repository_url": "https://i18n.elypia.org/api/projects/alexis/repository/",
          "statistics_url": "https://i18n.elypia.org/api/projects/alexis/statistics/",
          "changes_list_url": "https://i18n.elypia.org/api/projects/alexis/changes/",
          "languages_url": "https://i18n.elypia.org/api/projects/alexis/languages/"
        },
        "vcs": "gitlab",
        "repo": "git@gitlab.com:Elypia/alexis.git",
        "git_export": "https://i18n.elypia.org/git/alexis/alexis-messages/",
        "branch": "master",
        "filemask": "core/src/main/resources/org/elypia/alexis/i18n/AlexisMessages_*.properties",
        "template": "core/src/main/resources/org/elypia/alexis/i18n/AlexisMessages.properties",
        "edit_template": true,
        "new_base": "",
        "file_format": "properties-utf8",
        "license": "Apache-2.0",
        "license_url": "http://www.apache.org/licenses/LICENSE-2.0",
        "web_url": "https://i18n.elypia.org/projects/alexis/alexis-messages/",
        "url": "https://i18n.elypia.org/api/components/alexis/alexis-messages/",
        "repository_url": "https://i18n.elypia.org/api/components/alexis/alexis-messages/repository/",
        "translations_url": "https://i18n.elypia.org/api/components/alexis/alexis-messages/translations/",
        "statistics_url": "https://i18n.elypia.org/api/components/alexis/alexis-messages/statistics/",
        "lock_url": "https://i18n.elypia.org/api/components/alexis/alexis-messages/lock/",
        "changes_list_url": "https://i18n.elypia.org/api/components/alexis/alexis-messages/changes/",
        "new_lang": "add",
        "push": "",
        "check_flags": "",
        "enforced_checks": "",
        "restricted": false
      },
      "language_code": "no",
      "id": 68,
      "filename": "core/src/main/resources/org/elypia/alexis/i18n/AlexisMessages_no.properties",
      "revision": "5838e5c9dabbd41cc8f01782e4a81c22339a5630,a7a32c6b95988dca3a87e8c713a7f04613689228",
      "web_url": "https://i18n.elypia.org/projects/alexis/alexis-messages/nb_NO/",
      "share_url": "https://i18n.elypia.org/engage/alexis/nb_NO/",
      "translate_url": "https://i18n.elypia.org/translate/alexis/alexis-messages/nb_NO/",
      "url": "https://i18n.elypia.org/api/translations/alexis/alexis-messages/nb_NO/",
      "is_template": false,
      "is_source": false,
      "total": 202,
      "total_words": 1360,
      "translated": 34,
      "translated_words": 127,
      "translated_percent": 16.8,
      "fuzzy": 0,
      "fuzzy_words": 0,
      "fuzzy_percent": 0.0,
      "failing_checks": 4,
      "failing_checks_words": 33,
      "failing_checks_percent": 1.9,
      "have_suggestion": 0,
      "have_comment": 0,
      "last_change": null,
      "last_author": null,
      "repository_url": "https://i18n.elypia.org/api/translations/alexis/alexis-messages/nb_NO/repository/",
      "file_url": "https://i18n.elypia.org/api/translations/alexis/alexis-messages/nb_NO/file/",
      "statistics_url": "https://i18n.elypia.org/api/translations/alexis/alexis-messages/nb_NO/statistics/",
      "changes_list_url": "https://i18n.elypia.org/api/translations/alexis/alexis-messages/nb_NO/changes/",
      "units_list_url": "https://i18n.elypia.org/api/translations/alexis/alexis-messages/nb_NO/units/"
    },
    {
      "language": {
        "code": "pl",
        "name": "Polish",
        "plural": {
          "id": 250,
          "source": 0,
          "number": 3,
          "formula": "n==1 ? 0 : n%10>=2 && n%10<=4 && (n%100<10 || n%100>=20) ? 1 : 2",
          "type": 2
        },
        "aliases": [
          "polish",
          "pol"
        ],
        "direction": "ltr",
        "web_url": "https://i18n.elypia.org/languages/pl/",
        "url": "https://i18n.elypia.org/api/languages/pl/",
        "statistics_url": "https://i18n.elypia.org/api/languages/pl/statistics/"
      },
      "component": {
        "name": "Alexis Messages",
        "slug": "alexis-messages",
        "id": 6,
        "project": {
          "name": "Alexis",
          "slug": "alexis",
          "id": 5,
          "web": "https://elypia.org/",
          "source_language": {
            "code": "en",
            "name": "English",
            "plural": {
              "id": 80,
              "source": 0,
              "number": 2,
              "formula": "n != 1",
              "type": 1
            },
            "aliases": [
              "english",
              "en_en",
              "base",
              "source",
              "eng"
            ],
            "direction": "ltr",
            "web_url": "https://i18n.elypia.org/languages/en/",
            "url": "https://i18n.elypia.org/api/languages/en/",
            "statistics_url": "https://i18n.elypia.org/api/languages/en/statistics/"
          },
          "web_url": "https://i18n.elypia.org/projects/alexis/",
          "url": "https://i18n.elypia.org/api/projects/alexis/",
          "components_list_url": "https://i18n.elypia.org/api/projects/alexis/components/",
          "repository_url": "https://i18n.elypia.org/api/projects/alexis/repository/",
          "statistics_url": "https://i18n.elypia.org/api/projects/alexis/statistics/",
          "changes_list_url": "https://i18n.elypia.org/api/projects/alexis/changes/",
          "languages_url": "https://i18n.elypia.org/api/projects/alexis/languages/"
        },
        "vcs": "gitlab",
        "repo": "git@gitlab.com:Elypia/alexis.git",
        "git_export": "https://i18n.elypia.org/git/alexis/alexis-messages/",
        "branch": "master",
        "filemask": "core/src/main/resources/org/elypia/alexis/i18n/AlexisMessages_*.properties",
        "template": "core/src/main/resources/org/elypia/alexis/i18n/AlexisMessages.properties",
        "edit_template": true,
        "new_base": "",
        "file_format": "properties-utf8",
        "license": "Apache-2.0",
        "license_url": "http://www.apache.org/licenses/LICENSE-2.0",
        "web_url": "https://i18n.elypia.org/projects/alexis/alexis-messages/",
        "url": "https://i18n.elypia.org/api/components/alexis/alexis-messages/",
        "repository_url": "https://i18n.elypia.org/api/components/alexis/alexis-messages/repository/",
        "translations_url": "https://i18n.elypia.org/api/components/alexis/alexis-messages/translations/",
        "statistics_url": "https://i18n.elypia.org/api/components/alexis/alexis-messages/statistics/",
        "lock_url": "https://i18n.elypia.org/api/components/alexis/alexis-messages/lock/",
        "changes_list_url": "https://i18n.elypia.org/api/components/alexis/alexis-messages/changes/",
        "new_lang": "add",
        "push": "",
        "check_flags": "",
        "enforced_checks": "",
        "restricted": false
      },
      "language_code": "pl",
      "id": 69,
      "filename": "core/src/main/resources/org/elypia/alexis/i18n/AlexisMessages_pl.properties",
      "revision": "c98cc682d05731e475c66b5092d9ac3a387ed7f5,a7a32c6b95988dca3a87e8c713a7f04613689228",
      "web_url": "https://i18n.elypia.org/projects/alexis/alexis-messages/pl/",
      "share_url": "https://i18n.elypia.org/engage/alexis/pl/",
      "translate_url": "https://i18n.elypia.org/translate/alexis/alexis-messages/pl/",
      "url": "https://i18n.elypia.org/api/translations/alexis/alexis-messages/pl/",
      "is_template": false,
      "is_source": false,
      "total": 202,
      "total_words": 1360,
      "translated": 85,
      "translated_words": 565,
      "translated_percent": 42.0,
      "fuzzy": 0,
      "fuzzy_words": 0,
      "fuzzy_percent": 0.0,
      "failing_checks": 10,
      "failing_checks_words": 83,
      "failing_checks_percent": 4.9,
      "have_suggestion": 0,
      "have_comment": 0,
      "last_change": null,
      "last_author": null,
      "repository_url": "https://i18n.elypia.org/api/translations/alexis/alexis-messages/pl/repository/",
      "file_url": "https://i18n.elypia.org/api/translations/alexis/alexis-messages/pl/file/",
      "statistics_url": "https://i18n.elypia.org/api/translations/alexis/alexis-messages/pl/statistics/",
      "changes_list_url": "https://i18n.elypia.org/api/translations/alexis/alexis-messages/pl/changes/",
      "units_list_url": "https://i18n.elypia.org/api/translations/alexis/alexis-messages/pl/units/"
    },
    {
      "language": {
        "code": "en",
        "name": "English",
        "plural": {
          "id": 80,
          "source": 0,
          "number": 2,
          "formula": "n != 1",
          "type": 1
        },
        "aliases": [
          "english",
          "en_en",
          "base",
          "source",
          "eng"
        ],
        "direction": "ltr",
        "web_url": "https://i18n.elypia.org/languages/en/",
        "url": "https://i18n.elypia.org/api/languages/en/",
        "statistics_url": "https://i18n.elypia.org/api/languages/en/statistics/"
      },
      "component": {
        "name": "Commandler Messages",
        "slug": "commandler-messages",
        "id": 7,
        "project": {
          "name": "Alexis",
          "slug": "alexis",
          "id": 5,
          "web": "https://elypia.org/",
          "source_language": {
            "code": "en",
            "name": "English",
            "plural": {
              "id": 80,
              "source": 0,
              "number": 2,
              "formula": "n != 1",
              "type": 1
            },
            "aliases": [
              "english",
              "en_en",
              "base",
              "source",
              "eng"
            ],
            "direction": "ltr",
            "web_url": "https://i18n.elypia.org/languages/en/",
            "url": "https://i18n.elypia.org/api/languages/en/",
            "statistics_url": "https://i18n.elypia.org/api/languages/en/statistics/"
          },
          "web_url": "https://i18n.elypia.org/projects/alexis/",
          "url": "https://i18n.elypia.org/api/projects/alexis/",
          "components_list_url": "https://i18n.elypia.org/api/projects/alexis/components/",
          "repository_url": "https://i18n.elypia.org/api/projects/alexis/repository/",
          "statistics_url": "https://i18n.elypia.org/api/projects/alexis/statistics/",
          "changes_list_url": "https://i18n.elypia.org/api/projects/alexis/changes/",
          "languages_url": "https://i18n.elypia.org/api/projects/alexis/languages/"
        },
        "vcs": "git",
        "repo": "git@gitlab.com:Elypia/alexis.git",
        "git_export": "",
        "branch": "",
        "filemask": "core/src/main/resources/org/elypia/alexis/i18n/CommandlerMessages_*.properties",
        "template": "core/src/main/resources/org/elypia/alexis/i18n/CommandlerMessages.properties",
        "edit_template": true,
        "new_base": "",
        "file_format": "properties-utf8",
        "license": "Apache-2.0",
        "license_url": "http://www.apache.org/licenses/LICENSE-2.0",
        "web_url": "https://i18n.elypia.org/projects/alexis/commandler-messages/",
        "url": "https://i18n.elypia.org/api/components/alexis/commandler-messages/",
        "repository_url": "https://i18n.elypia.org/api/components/alexis/commandler-messages/repository/",
        "translations_url": "https://i18n.elypia.org/api/components/alexis/commandler-messages/translations/",
        "statistics_url": "https://i18n.elypia.org/api/components/alexis/commandler-messages/statistics/",
        "lock_url": "https://i18n.elypia.org/api/components/alexis/commandler-messages/lock/",
        "changes_list_url": "https://i18n.elypia.org/api/components/alexis/commandler-messages/changes/",
        "new_lang": "add",
        "push": "",
        "check_flags": "",
        "enforced_checks": "[]",
        "restricted": false
      },
      "language_code": "en",
      "id": 70,
      "filename": "core/src/main/resources/org/elypia/alexis/i18n/CommandlerMessages.properties",
      "revision": "e0f4ede69ca7e43e9bd000f86436f934fb03648c,e0f4ede69ca7e43e9bd000f86436f934fb03648c",
      "web_url": "https://i18n.elypia.org/projects/alexis/commandler-messages/en/",
      "share_url": "https://i18n.elypia.org/engage/alexis/en/",
      "translate_url": "https://i18n.elypia.org/translate/alexis/commandler-messages/en/",
      "url": "https://i18n.elypia.org/api/translations/alexis/commandler-messages/en/",
      "is_template": true,
      "is_source": true,
      "total": 473,
      "total_words": 1736,
      "translated": 473,
      "translated_words": 1736,
      "translated_percent": 100.0,
      "fuzzy": 0,
      "fuzzy_words": 0,
      "fuzzy_percent": 0.0,
      "failing_checks": 48,
      "failing_checks_words": 290,
      "failing_checks_percent": 10.1,
      "have_suggestion": 0,
      "have_comment": 0,
      "last_change": null,
      "last_author": null,
      "repository_url": "https://i18n.elypia.org/api/translations/alexis/commandler-messages/en/repository/",
      "file_url": "https://i18n.elypia.org/api/translations/alexis/commandler-messages/en/file/",
      "statistics_url": "https://i18n.elypia.org/api/translations/alexis/commandler-messages/en/statistics/",
      "changes_list_url": "https://i18n.elypia.org/api/translations/alexis/commandler-messages/en/changes/",
      "units_list_url": "https://i18n.elypia.org/api/translations/alexis/commandler-messages/en/units/"
    },
    {
      "language": {
        "code": "bs",
        "name": "Bosnian",
        "plural": {
          "id": 46,
          "source": 0,
          "number": 3,
          "formula": "n%10==1 && n%100!=11 ? 0 : n%10>=2 && n%10<=4 && (n%100<10 || n%100>=20) ? 1 : 2",
          "type": 2
        },
        "aliases": [
          "bos"
        ],
        "direction": "ltr",
        "web_url": "https://i18n.elypia.org/languages/bs/",
        "url": "https://i18n.elypia.org/api/languages/bs/",
        "statistics_url": "https://i18n.elypia.org/api/languages/bs/statistics/"
      },
      "component": {
        "name": "Commandler Messages",
        "slug": "commandler-messages",
        "id": 7,
        "project": {
          "name": "Alexis",
          "slug": "alexis",
          "id": 5,
          "web": "https://elypia.org/",
          "source_language": {
            "code": "en",
            "name": "English",
            "plural": {
              "id": 80,
              "source": 0,
              "number": 2,
              "formula": "n != 1",
              "type": 1
            },
            "aliases": [
              "english",
              "en_en",
              "base",
              "source",
              "eng"
            ],
            "direction": "ltr",
            "web_url": "https://i18n.elypia.org/languages/en/",
            "url": "https://i18n.elypia.org/api/languages/en/",
            "statistics_url": "https://i18n.elypia.org/api/languages/en/statistics/"
          },
          "web_url": "https://i18n.elypia.org/projects/alexis/",
          "url": "https://i18n.elypia.org/api/projects/alexis/",
          "components_list_url": "https://i18n.elypia.org/api/projects/alexis/components/",
          "repository_url": "https://i18n.elypia.org/api/projects/alexis/repository/",
          "statistics_url": "https://i18n.elypia.org/api/projects/alexis/statistics/",
          "changes_list_url": "https://i18n.elypia.org/api/projects/alexis/changes/",
          "languages_url": "https://i18n.elypia.org/api/projects/alexis/languages/"
        },
        "vcs": "git",
        "repo": "git@gitlab.com:Elypia/alexis.git",
        "git_export": "",
        "branch": "",
        "filemask": "core/src/main/resources/org/elypia/alexis/i18n/CommandlerMessages_*.properties",
        "template": "core/src/main/resources/org/elypia/alexis/i18n/CommandlerMessages.properties",
        "edit_template": true,
        "new_base": "",
        "file_format": "properties-utf8",
        "license": "Apache-2.0",
        "license_url": "http://www.apache.org/licenses/LICENSE-2.0",
        "web_url": "https://i18n.elypia.org/projects/alexis/commandler-messages/",
        "url": "https://i18n.elypia.org/api/components/alexis/commandler-messages/",
        "repository_url": "https://i18n.elypia.org/api/components/alexis/commandler-messages/repository/",
        "translations_url": "https://i18n.elypia.org/api/components/alexis/commandler-messages/translations/",
        "statistics_url": "https://i18n.elypia.org/api/components/alexis/commandler-messages/statistics/",
        "lock_url": "https://i18n.elypia.org/api/components/alexis/commandler-messages/lock/",
        "changes_list_url": "https://i18n.elypia.org/api/components/alexis/commandler-messages/changes/",
        "new_lang": "add",
        "push": "",
        "check_flags": "",
        "enforced_checks": "[]",
        "restricted": false
      },
      "language_code": "bs",
      "id": 71,
      "filename": "core/src/main/resources/org/elypia/alexis/i18n/CommandlerMessages_bs.properties",
      "revision": "ec8d82c9bdb821996971507faa788afa562054e8,e0f4ede69ca7e43e9bd000f86436f934fb03648c",
      "web_url": "https://i18n.elypia.org/projects/alexis/commandler-messages/bs/",
      "share_url": "https://i18n.elypia.org/engage/alexis/bs/",
      "translate_url": "https://i18n.elypia.org/translate/alexis/commandler-messages/bs/",
      "url": "https://i18n.elypia.org/api/translations/alexis/commandler-messages/bs/",
      "is_template": false,
      "is_source": false,
      "total": 473,
      "total_words": 1736,
      "translated": 209,
      "translated_words": 1069,
      "translated_percent": 44.1,
      "fuzzy": 0,
      "fuzzy_words": 0,
      "fuzzy_percent": 0.0,
      "failing_checks": 26,
      "failing_checks_words": 216,
      "failing_checks_percent": 5.4,
      "have_suggestion": 0,
      "have_comment": 0,
      "last_change": null,
      "last_author": null,
      "repository_url": "https://i18n.elypia.org/api/translations/alexis/commandler-messages/bs/repository/",
      "file_url": "https://i18n.elypia.org/api/translations/alexis/commandler-messages/bs/file/",
      "statistics_url": "https://i18n.elypia.org/api/translations/alexis/commandler-messages/bs/statistics/",
      "changes_list_url": "https://i18n.elypia.org/api/translations/alexis/commandler-messages/bs/changes/",
      "units_list_url": "https://i18n.elypia.org/api/translations/alexis/commandler-messages/bs/units/"
    },
    {
      "language": {
        "code": "da",
        "name": "Danish",
        "plural": {
          "id": 69,
          "source": 0,
          "number": 2,
          "formula": "n != 1",
          "type": 1
        },
        "aliases": [
          "dk",
          "dan"
        ],
        "direction": "ltr",
        "web_url": "https://i18n.elypia.org/languages/da/",
        "url": "https://i18n.elypia.org/api/languages/da/",
        "statistics_url": "https://i18n.elypia.org/api/languages/da/statistics/"
      },
      "component": {
        "name": "Commandler Messages",
        "slug": "commandler-messages",
        "id": 7,
        "project": {
          "name": "Alexis",
          "slug": "alexis",
          "id": 5,
          "web": "https://elypia.org/",
          "source_language": {
            "code": "en",
            "name": "English",
            "plural": {
              "id": 80,
              "source": 0,
              "number": 2,
              "formula": "n != 1",
              "type": 1
            },
            "aliases": [
              "english",
              "en_en",
              "base",
              "source",
              "eng"
            ],
            "direction": "ltr",
            "web_url": "https://i18n.elypia.org/languages/en/",
            "url": "https://i18n.elypia.org/api/languages/en/",
            "statistics_url": "https://i18n.elypia.org/api/languages/en/statistics/"
          },
          "web_url": "https://i18n.elypia.org/projects/alexis/",
          "url": "https://i18n.elypia.org/api/projects/alexis/",
          "components_list_url": "https://i18n.elypia.org/api/projects/alexis/components/",
          "repository_url": "https://i18n.elypia.org/api/projects/alexis/repository/",
          "statistics_url": "https://i18n.elypia.org/api/projects/alexis/statistics/",
          "changes_list_url": "https://i18n.elypia.org/api/projects/alexis/changes/",
          "languages_url": "https://i18n.elypia.org/api/projects/alexis/languages/"
        },
        "vcs": "git",
        "repo": "git@gitlab.com:Elypia/alexis.git",
        "git_export": "",
        "branch": "",
        "filemask": "core/src/main/resources/org/elypia/alexis/i18n/CommandlerMessages_*.properties",
        "template": "core/src/main/resources/org/elypia/alexis/i18n/CommandlerMessages.properties",
        "edit_template": true,
        "new_base": "",
        "file_format": "properties-utf8",
        "license": "Apache-2.0",
        "license_url": "http://www.apache.org/licenses/LICENSE-2.0",
        "web_url": "https://i18n.elypia.org/projects/alexis/commandler-messages/",
        "url": "https://i18n.elypia.org/api/components/alexis/commandler-messages/",
        "repository_url": "https://i18n.elypia.org/api/components/alexis/commandler-messages/repository/",
        "translations_url": "https://i18n.elypia.org/api/components/alexis/commandler-messages/translations/",
        "statistics_url": "https://i18n.elypia.org/api/components/alexis/commandler-messages/statistics/",
        "lock_url": "https://i18n.elypia.org/api/components/alexis/commandler-messages/lock/",
        "changes_list_url": "https://i18n.elypia.org/api/components/alexis/commandler-messages/changes/",
        "new_lang": "add",
        "push": "",
        "check_flags": "",
        "enforced_checks": "[]",
        "restricted": false
      },
      "language_code": "da",
      "id": 72,
      "filename": "core/src/main/resources/org/elypia/alexis/i18n/CommandlerMessages_da.properties",
      "revision": "86f6d74535572f05070b862b652532f9f45ac30c,e0f4ede69ca7e43e9bd000f86436f934fb03648c",
      "web_url": "https://i18n.elypia.org/projects/alexis/commandler-messages/da/",
      "share_url": "https://i18n.elypia.org/engage/alexis/da/",
      "translate_url": "https://i18n.elypia.org/translate/alexis/commandler-messages/da/",
      "url": "https://i18n.elypia.org/api/translations/alexis/commandler-messages/da/",
      "is_template": false,
      "is_source": false,
      "total": 473,
      "total_words": 1736,
      "translated": 9,
      "translated_words": 76,
      "translated_percent": 1.9,
      "fuzzy": 0,
      "fuzzy_words": 0,
      "fuzzy_percent": 0.0,
      "failing_checks": 5,
      "failing_checks_words": 46,
      "failing_checks_percent": 1.0,
      "have_suggestion": 0,
      "have_comment": 0,
      "last_change": null,
      "last_author": null,
      "repository_url": "https://i18n.elypia.org/api/translations/alexis/commandler-messages/da/repository/",
      "file_url": "https://i18n.elypia.org/api/translations/alexis/commandler-messages/da/file/",
      "statistics_url": "https://i18n.elypia.org/api/translations/alexis/commandler-messages/da/statistics/",
      "changes_list_url": "https://i18n.elypia.org/api/translations/alexis/commandler-messages/da/changes/",
      "units_list_url": "https://i18n.elypia.org/api/translations/alexis/commandler-messages/da/units/"
    },
    {
      "language": {
        "code": "de",
        "name": "German",
        "plural": {
          "id": 70,
          "source": 0,
          "number": 2,
          "formula": "n != 1",
          "type": 1
        },
        "aliases": [
          "german",
          "deu",
          "ger"
        ],
        "direction": "ltr",
        "web_url": "https://i18n.elypia.org/languages/de/",
        "url": "https://i18n.elypia.org/api/languages/de/",
        "statistics_url": "https://i18n.elypia.org/api/languages/de/statistics/"
      },
      "component": {
        "name": "Commandler Messages",
        "slug": "commandler-messages",
        "id": 7,
        "project": {
          "name": "Alexis",
          "slug": "alexis",
          "id": 5,
          "web": "https://elypia.org/",
          "source_language": {
            "code": "en",
            "name": "English",
            "plural": {
              "id": 80,
              "source": 0,
              "number": 2,
              "formula": "n != 1",
              "type": 1
            },
            "aliases": [
              "english",
              "en_en",
              "base",
              "source",
              "eng"
            ],
            "direction": "ltr",
            "web_url": "https://i18n.elypia.org/languages/en/",
            "url": "https://i18n.elypia.org/api/languages/en/",
            "statistics_url": "https://i18n.elypia.org/api/languages/en/statistics/"
          },
          "web_url": "https://i18n.elypia.org/projects/alexis/",
          "url": "https://i18n.elypia.org/api/projects/alexis/",
          "components_list_url": "https://i18n.elypia.org/api/projects/alexis/components/",
          "repository_url": "https://i18n.elypia.org/api/projects/alexis/repository/",
          "statistics_url": "https://i18n.elypia.org/api/projects/alexis/statistics/",
          "changes_list_url": "https://i18n.elypia.org/api/projects/alexis/changes/",
          "languages_url": "https://i18n.elypia.org/api/projects/alexis/languages/"
        },
        "vcs": "git",
        "repo": "git@gitlab.com:Elypia/alexis.git",
        "git_export": "",
        "branch": "",
        "filemask": "core/src/main/resources/org/elypia/alexis/i18n/CommandlerMessages_*.properties",
        "template": "core/src/main/resources/org/elypia/alexis/i18n/CommandlerMessages.properties",
        "edit_template": true,
        "new_base": "",
        "file_format": "properties-utf8",
        "license": "Apache-2.0",
        "license_url": "http://www.apache.org/licenses/LICENSE-2.0",
        "web_url": "https://i18n.elypia.org/projects/alexis/commandler-messages/",
        "url": "https://i18n.elypia.org/api/components/alexis/commandler-messages/",
        "repository_url": "https://i18n.elypia.org/api/components/alexis/commandler-messages/repository/",
        "translations_url": "https://i18n.elypia.org/api/components/alexis/commandler-messages/translations/",
        "statistics_url": "https://i18n.elypia.org/api/components/alexis/commandler-messages/statistics/",
        "lock_url": "https://i18n.elypia.org/api/components/alexis/commandler-messages/lock/",
        "changes_list_url": "https://i18n.elypia.org/api/components/alexis/commandler-messages/changes/",
        "new_lang": "add",
        "push": "",
        "check_flags": "",
        "enforced_checks": "[]",
        "restricted": false
      },
      "language_code": "de",
      "id": 73,
      "filename": "core/src/main/resources/org/elypia/alexis/i18n/CommandlerMessages_de.properties",
      "revision": "9ae2b842190a2ad86a35863260974e0f56dd7ef8,e0f4ede69ca7e43e9bd000f86436f934fb03648c",
      "web_url": "https://i18n.elypia.org/projects/alexis/commandler-messages/de/",
      "share_url": "https://i18n.elypia.org/engage/alexis/de/",
      "translate_url": "https://i18n.elypia.org/translate/alexis/commandler-messages/de/",
      "url": "https://i18n.elypia.org/api/translations/alexis/commandler-messages/de/",
      "is_template": false,
      "is_source": false,
      "total": 473,
      "total_words": 1736,
      "translated": 246,
      "translated_words": 1201,
      "translated_percent": 52.0,
      "fuzzy": 0,
      "fuzzy_words": 0,
      "fuzzy_percent": 0.0,
      "failing_checks": 60,
      "failing_checks_words": 375,
      "failing_checks_percent": 12.6,
      "have_suggestion": 0,
      "have_comment": 0,
      "last_change": null,
      "last_author": null,
      "repository_url": "https://i18n.elypia.org/api/translations/alexis/commandler-messages/de/repository/",
      "file_url": "https://i18n.elypia.org/api/translations/alexis/commandler-messages/de/file/",
      "statistics_url": "https://i18n.elypia.org/api/translations/alexis/commandler-messages/de/statistics/",
      "changes_list_url": "https://i18n.elypia.org/api/translations/alexis/commandler-messages/de/changes/",
      "units_list_url": "https://i18n.elypia.org/api/translations/alexis/commandler-messages/de/units/"
    }
  ]
}
